kudapy/__init__.py
kudapy/base_api.py
kudapy/example.py
kudapy/exceptions.py
kudapy/kuda.py
kudapy/utils.py
kudapy/version.py
kudapy/algorithms/__init__.py
kudapy/algorithms/aes_algorithm.py
kudapy/algorithms/rsa_algorithm.py
tests/__init__.py
tests/test_kuda.py
kudapy-2.0.dist-info/LICENSE
kudapy-2.0.dist-info/METADATA
kudapy-2.0.dist-info/WHEEL
kudapy-2.0.dist-info/top_level.txt
kudapy-2.0.dist-info/RECORD
