Metadata-Version: 2.1
Name: kudapy
Version: 2.0
Summary: Python wrapper for making secure requests to Kuda API
Home-page: https://github.com/daleentontech/kudapy
Author: Uchechukwu Darlington Emmanuel
Author-email: daleentontech@gmail.com
License: UNKNOWN
Project-URL: Source, https://github.com/daleentontech/kudapy/
Platform: UNKNOWN
Classifier: Programming Language :: Python :: 3
Classifier: License :: OSI Approved :: MIT License
Classifier: Operating System :: OS Independent
Requires-Python: >=3.6
Requires-Dist: requests
Requires-Dist: pycryptodome
